wb_mcp_dome/__init__.py
wb_mcp_dome-0.1.0.dist-info/WHEEL
wb_mcp_dome-0.1.0.dist-info/entry_points.txt
wb_mcp_dome-0.1.0.dist-info/METADATA
wb_mcp_dome-0.1.0.dist-info/RECORD
