Metadata-Version: 2.3
Name: wb-mcp-dome
Version: 0.1.0
Summary: Add your description here
Requires-Dist: mcp[cli]>=1.13.1
Requires-Python: >=3.13
